<?xml version="1.0" encoding="UTF-8"?><?xml-stylesheet type="text/xsl" href="Result.xsl"?>
<TestSuite EndTime="09-30-2014 18:16:50" StartTime="09-30-2014 18:15:07"
	TF="1" TP="0" TotalTestCases="1">
	<Functionality name="CBDT">
		<TestScript EndTime="09-30-2014 18:16:50" StartTime="09-30-2014 18:15:07"
			TC_Status="Fail" name="CBDT_CLEAR_TC3">
			<Iterator no="0">
				<step no="1">
					<status>Pass</status>
					<stepname>Login to Finacle application with valid maker credentials
					</stepname>
					<Description>Sucessfully logged in to finacle application with
						maker credentials</Description>
					<timestamp>09-30-2014 18:15:07</timestamp>
				</step>
				<step no="2">
					<status>Pass</status>
					<stepname>Get the Instrument id from application</stepname>
					<Description>Unused Instrument id is:573620</Description>
					<timestamp>09-30-2014 18:15:27</timestamp>
				</step>
				<step no="3">
					<status>Pass</status>
					<stepname>Create a Zone for Clear transaction </stepname>
					<Description>Zone Code created:Zone - 069/30-09-2014/ATPAROUT
						Opened successfully.</Description>
					<timestamp>09-30-2014 18:15:42</timestamp>
				</step>
				<step no="4">
					<status>Pass</status>
					<stepname> Navigate GBM from finacle</stepname>
					<Description>Government Business Modulepage is displayed
					</Description>
					<timestamp>09-30-2014 18:16:05</timestamp>
				</step>
				<step no="5">
					<status>Fail</status>
					<stepname>Failed to open create transaction page</stepname>
					<Description>Navigation failed. Error Message:Transaction
						maintenanceOLTAS TRANSACTION MAINTENANCEis not visible
					</Description>
					<timestamp>09-30-2014 18:16:47</timestamp>
				</step>
				<step no="6">
					<status>Pass</status>
					<stepname>Logout from application</stepname>
					<Description>User successfully logged out from application
					</Description>
					<timestamp>09-30-2014 18:16:50</timestamp>
				</step>
			</Iterator>
		</TestScript>
	</Functionality>
</TestSuite>